llama_index/readers/genius/__init__.py
llama_index/readers/genius/base.py
llama_index_readers_genius-0.4.1.dist-info/METADATA
llama_index_readers_genius-0.4.1.dist-info/WHEEL
llama_index_readers_genius-0.4.1.dist-info/licenses/LICENSE
llama_index_readers_genius-0.4.1.dist-info/RECORD
